<?xml version="1.0" encoding="utf-8" ?>
<dwsync>
<file name="Etermal.html" server="D:/My Drive/DRF Website/www/" local="130882317850000000" remote="130882317850000000" Dst="2" />
<file name="index.html" server="D:/My Drive/DRF Website/www/" local="130882317850000000" remote="130882317850000000" Dst="2" />
<file name="jquery-ui.css" server="D:/My Drive/DRF Website/www/" local="130882317850000000" remote="130882317850000000" Dst="2" />
<file name="jquery-ui.js" server="D:/My Drive/DRF Website/www/" local="130882317850000000" remote="130882317850000000" Dst="2" />
<file name="jquery-ui.min.css" server="D:/My Drive/DRF Website/www/" local="130882317850000000" remote="130882317850000000" Dst="2" />
<file name="jquery-ui.min.js" server="D:/My Drive/DRF Website/www/" local="130882317850000000" remote="130882317850000000" Dst="2" />
<file name="jquery-ui.structure.css" server="D:/My Drive/DRF Website/www/" local="130882317850000000" remote="130882317850000000" Dst="2" />
<file name="jquery-ui.structure.min.css" server="D:/My Drive/DRF Website/www/" local="130882317850000000" remote="130882317850000000" Dst="2" />
<file name="jquery-ui.theme.css" server="D:/My Drive/DRF Website/www/" local="130882317850000000" remote="130882317850000000" Dst="2" />
<file name="jquery-ui.theme.min.css" server="D:/My Drive/DRF Website/www/" local="130882317850000000" remote="130882317850000000" Dst="2" />
</dwsync>